ExpressLibrary/__init__.py
ExpressLibrary/data-handler.py
ExpressLibrary/visualizations/__init__.py
ExpressLibrary/visualizations/bar_chart.py
ExpressLibrary/visualizations/base_bar_chart.py
ExpressLibrary/visualizations/base_heatmap.py
ExpressLibrary/visualizations/base_hierarchical_chart.py
ExpressLibrary/visualizations/base_packing_chart.py
ExpressLibrary/visualizations/circle_packing_chart.py
ExpressLibrary/visualizations/heatmap_chart.py
ExpressLibrary/visualizations/hierarchical_network_chart.py
ExpressLibrary/visualizations/scatter_plot.py
ExpressLibrary-0.1.0.dist-info/METADATA
ExpressLibrary-0.1.0.dist-info/WHEEL
ExpressLibrary-0.1.0.dist-info/top_level.txt
ExpressLibrary-0.1.0.dist-info/RECORD
