Metadata-Version: 2.1
Name: ExpressLibrary
Version: 0.1.0
Summary: Express library is a Python package designed to streamline the data visualization process in a consultancy environment. This package aims to facilitate the quick transformation of data into insightful visualizations. It is developed on top of standard libraries such as Plotly and Circlify.
Home-page: https://github.com/shahid265/ExpressLibrary.git
Author: Shahid
Author-email: shahid265.sr@gmail.com
Requires-Dist: plotly
Requires-Dist: pandas
Requires-Dist: circlify
Requires-Dist: matplotlib
Requires-Dist: pytest
